qiufeng/__init__.py
qiufeng/main.py
qiufeng-1.3.1.dist-info/METADATA
qiufeng-1.3.1.dist-info/WHEEL
qiufeng-1.3.1.dist-info/RECORD
