Metadata-Version: 2.3
Name: qiufeng
Version: 1.3.1
Summary: This is my first package
Author: qiufeng
Author-email: appleidqiufeng@outlook.com
Requires-Python: >=3.8,<4.0
Classifier: Programming Language :: Python :: 3
Classifier: Programming Language :: Python :: 3.8
Classifier: Programming Language :: Python :: 3.9
Classifier: Programming Language :: Python :: 3.10
Classifier: Programming Language :: Python :: 3.11
Classifier: Programming Language :: Python :: 3.12
Classifier: Programming Language :: Python :: 3.13
Requires-Dist: pyfiglet
Requires-Dist: pynput
